{"$schema":"https://vega.github.io/schema/vega-lite/v4.json","width":"container","height":"container","data":{"name":null},"encoding":{"x":{"field":"x","type":"quantitative","scale":{"domain":[null,null]},"axis":{"title":null,"grid":false,"ticks":false,"labels":false,"domainColor":"lightgray"}},"y":{"field":"y","type":"quantitative","scale":{"domain":[null,null]},"axis":{"title":null,"grid":false,"ticks":false,"labels":false,"domainColor":"lightgray"}}},"layer":[{"mark":{"type":"line","clip":true},"encoding":{"order":{"field":"group","type":"quantitative"},"color":{"value":"black"}}},{"mark":{"type":"text","align":"center","dy":-3},"encoding":{"text":{"field":"axis_name","type":"nominal"}}}]}
