[
  {
    "package": "ahpsurvey",
    "on_cran": false,
    "archived_on": "2025-10-02 01:02:00",
    "url": "https://github.com/cranhaven/cranhaven.r-universe.dev",
    "branch": "package/ahpsurvey",
    "subdir": "ahpsurvey",
    "x_cran_comment_date": "2025-10-02",
    "x_cran_comment_event": "archived",
    "x_cran_comment_reason": "Check issues were not corrected in time",
    "maintainer": "Frankie Cho <htcho@connect.hku.hk>"
  },
  {
    "package": "aidar",
    "on_cran": false,
    "archived_on": "2025-09-28 08:02:00",
    "url": "https://github.com/cranhaven/cranhaven.r-universe.dev",
    "branch": "package/aidar",
    "subdir": "aidar",
    "x_cran_comment_date": "2025-09-28",
    "x_cran_comment_event": "archived",
    "x_cran_comment_reason": "Check problems were not corrected despite reminders",
    "maintainer": "Andreas Pfeiffer <apfeiffer1@gmail.com>"
  },
  {
    "package": "alpaca",
    "on_cran": false,
    "archived_on": "2025-09-17 08:02:00",
    "url": "https://github.com/cranhaven/cranhaven.r-universe.dev",
    "branch": "package/alpaca",
    "subdir": "alpaca",
    "x_cran_comment_date": "2025-09-17",
    "x_cran_comment_event": "archived",
    "x_cran_comment_reason": "Email to the maintainer is undeliverable",
    "package_url": "https://github.com/amrei-stammann/alpaca",
    "package_bugreports": "https://github.com/amrei-stammann/alpaca/issues",
    "maintainer": "Amrei Stammann <amrei.stammann@rub.de>"
  },
  {
    "package": "AntMAN",
    "on_cran": false,
    "archived_on": "2025-09-17 08:02:00",
    "url": "https://github.com/cranhaven/cranhaven.r-universe.dev",
    "branch": "package/AntMAN",
    "subdir": "AntMAN",
    "x_cran_comment_date": "2025-09-17",
    "x_cran_comment_event": "archived",
    "x_cran_comment_reason": "Email to the maintainer is undeliverable",
    "x_cran_history": "Archived on 2020-03-31 as installation problems were not corrected in time.\nUnarchived on 2021-07-23.",
    "package_url": "https://github.com/bbodin/AntMAN",
    "maintainer": "Bruno Bodin <bruno.bodin@yale-nus.edu.sg>"
  },
  {
    "package": "apLCMS",
    "on_cran": false,
    "archived_on": "2025-09-01 23:02:00",
    "url": "https://github.com/cranhaven/cranhaven.r-universe.dev",
    "branch": "package/apLCMS",
    "subdir": "apLCMS",
    "x_cran_comment_date": "2025-09-02",
    "x_cran_comment_event": "archived",
    "x_cran_comment_reason": "Errors were not corrected in time",
    "maintainer": "Tianwei Yu <yutianwei@cuhk.edu.cn>"
  },
  {
    "package": "Asiaverse",
    "on_cran": false,
    "archived_on": "2025-10-01 08:02:00",
    "url": "https://github.com/cranhaven/cranhaven.r-universe.dev",
    "branch": "package/Asiaverse",
    "subdir": "Asiaverse",
    "x_cran_comment_date": "2025-10-01",
    "x_cran_comment_event": "archived",
    "x_cran_comment_reason": "Qs requires archived package 'SouthKoreAPIs'",
    "package_url": "https://github.com/lightbluetitan/asiaverse,\nhttps://lightbluetitan.github.io/asiaverse/",
    "package_bugreports": "https://github.com/lightbluetitan/asiaverse/issues",
    "maintainer": "Renzo Caceres Rossi <arenzocaceresrossi@gmail.com>"
  },
  {
    "package": "bardr",
    "on_cran": false,
    "archived_on": "2025-09-19 09:02:00",
    "url": "https://github.com/cranhaven/cranhaven.r-universe.dev",
    "branch": "package/bardr",
    "subdir": "bardr",
    "x_cran_comment_date": "2025-09-19",
    "x_cran_comment_event": "archived",
    "x_cran_comment_reason": "The maintainer's request",
    "maintainer": "Zane Billings <wz.billings@gmail.com>"
  },
  {
    "package": "BayesReversePLLH",
    "on_cran": false,
    "archived_on": "2025-09-17 08:02:00",
    "url": "https://github.com/cranhaven/cranhaven.r-universe.dev",
    "branch": "package/BayesReversePLLH",
    "subdir": "BayesReversePLLH",
    "x_cran_comment_date": "2025-09-17",
    "x_cran_comment_event": "archived",
    "x_cran_comment_reason": "Email to the maintainer is undeliverable",
    "maintainer": "Andrew G Chapple <achapp@lsuhsc.edu>"
  },
  {
    "package": "BEAMR",
    "on_cran": false,
    "archived_on": "2025-09-17 08:02:00",
    "url": "https://github.com/cranhaven/cranhaven.r-universe.dev",
    "branch": "package/BEAMR",
    "subdir": "BEAMR",
    "x_cran_comment_date": "2025-09-17",
    "x_cran_comment_event": "archived",
    "x_cran_comment_reason": "Email to the maintainer is undeliverable",
    "package_url": "https://annaseffernick.github.io/BEAMR/,\nhttps://github.com/annaSeffernick/BEAMR",
    "package_bugreports": "https://github.com/annaSeffernick/BEAMR/issues",
    "maintainer": "Anna Eames Seffernick <anna.seffernick@stjude.org>"
  },
  {
    "package": "bife",
    "on_cran": false,
    "archived_on": "2025-09-17 08:02:00",
    "url": "https://github.com/cranhaven/cranhaven.r-universe.dev",
    "branch": "package/bife",
    "subdir": "bife",
    "x_cran_comment_date": "2025-09-17",
    "x_cran_comment_event": "archived",
    "x_cran_comment_reason": "Email to the maintainer is undeliverable",
    "package_url": "https://github.com/amrei-stammann/bife",
    "package_bugreports": "https://github.com/amrei-stammann/bife/issues",
    "maintainer": "Amrei Stammann <amrei.stammann@rub.de>"
  },
  {
    "package": "bisque",
    "on_cran": false,
    "archived_on": "2025-09-17 08:02:00",
    "url": "https://github.com/cranhaven/cranhaven.r-universe.dev",
    "branch": "package/bisque",
    "subdir": "bisque",
    "x_cran_comment_date": "2025-09-17",
    "x_cran_comment_event": "archived",
    "x_cran_comment_reason": "Email to the maintainer is undeliverable",
    "maintainer": "Joshua Hewitt <joshua.hewitt@duke.edu>"
  },
  {
    "package": "BrailleR",
    "on_cran": false,
    "archived_on": "2025-09-09 07:02:00",
    "url": "https://github.com/cranhaven/cranhaven.r-universe.dev",
    "branch": "package/BrailleR",
    "subdir": "BrailleR",
    "x_cran_comment_date": "2025-09-09",
    "x_cran_comment_event": "archived",
    "x_cran_comment_reason": "Requires archived package 'extrafont'",
    "x_cran_history": "Archived on 2019-11-10 as obsolete Python requirement was not corrected as requested.\nUnarchived on 2020-01-22.\nArchived on 2020-03-30 as check problems were not corrected in time.\n\nmissing labels after 'ggplot2' update.\nUnarchived on 2021-10-22.",
    "package_url": "https://github.com/ajrgodfrey/BrailleR,\nhttp://ajrgodfrey.github.io/BrailleR/",
    "package_bugreports": "https://github.com/ajrgodfrey/BrailleR/issues",
    "maintainer": "A. Jonathan R. Godfrey <a.j.godfrey@massey.ac.nz>"
  },
  {
    "package": "bridger",
    "on_cran": false,
    "archived_on": "2025-09-08 14:02:00",
    "url": "https://github.com/cranhaven/cranhaven.r-universe.dev",
    "branch": "package/bridger",
    "subdir": "bridger",
    "x_cran_comment_date": "2025-09-08",
    "x_cran_comment_event": "archived",
    "x_cran_comment_reason": "It depends on 'ggedit' which was archived",
    "package_url": "https://github.com/CommoditiesAI/bridger",
    "maintainer": "Jason Kaplan <scjase@gmail.com>"
  },
  {
    "package": "brpop",
    "on_cran": false,
    "archived_on": "2025-09-16 02:02:00",
    "url": "https://github.com/cranhaven/cranhaven.r-universe.dev",
    "branch": "package/brpop",
    "subdir": "brpop",
    "x_cran_comment_date": "2025-09-16",
    "x_cran_comment_event": "archived",
    "x_cran_comment_reason": "Policy violation. On Internet access",
    "package_url": "https://rfsaldanha.github.io/brpop/",
    "package_bugreports": "https://github.com/rfsaldanha/brpop/issues",
    "maintainer": "Raphael Saldanha <raphael.saldanha@fiocruz.br>"
  },
  {
    "package": "camelsCL",
    "on_cran": false,
    "archived_on": "2025-09-17 19:02:00",
    "url": "https://github.com/cranhaven/cranhaven.r-universe.dev",
    "branch": "package/camelsCL",
    "subdir": "camelsCL",
    "x_cran_comment_date": "2025-09-18",
    "x_cran_comment_event": "archived",
    "x_cran_comment_reason": "The maintainer's request",
    "package_url": "https://gitlab.com/hgarcesf/camelsCL",
    "package_bugreports": "https://gitlab.com/hgarcesf/camelsCL/-/issues",
    "maintainer": "Hector Garces-Figueroa <hegarcesf@gmail.com>"
  },
  {
    "package": "cesR",
    "on_cran": false,
    "archived_on": "2025-10-03 01:02:00",
    "url": "https://github.com/cranhaven/cranhaven.r-universe.dev",
    "branch": "package/cesR",
    "subdir": "cesR",
    "x_cran_comment_date": "2025-10-03",
    "x_cran_comment_event": "archived",
    "x_cran_comment_reason": "Check issues were not corrected in time",
    "package_url": "https://hodgettsp.github.io/cesR/",
    "package_bugreports": "https://github.com/hodgettsp/cesR/issues",
    "maintainer": "Paul A. Hodgetts <hodgetts.paul@outlook.com>"
  },
  {
    "package": "classifly",
    "on_cran": false,
    "archived_on": "2025-09-04 01:02:00",
    "url": "https://github.com/cranhaven/cranhaven.r-universe.dev",
    "branch": "package/classifly",
    "subdir": "classifly",
    "x_cran_comment_date": "2025-09-04",
    "x_cran_comment_event": "archived",
    "x_cran_comment_reason": "The maintainer's request",
    "package_url": "http://had.co.nz/classifly",
    "maintainer": "Hadley Wickham <h.wickham@gmail.com>"
  },
  {
    "package": "corrcoverage",
    "on_cran": false,
    "archived_on": "2025-09-17 08:02:00",
    "url": "https://github.com/cranhaven/cranhaven.r-universe.dev",
    "branch": "package/corrcoverage",
    "subdir": "corrcoverage",
    "x_cran_comment_date": "2025-09-17",
    "x_cran_comment_event": "archived",
    "x_cran_comment_reason": "Email to the maintainer is undeliverable",
    "package_url": "https://annahutch.github.io/corrcoverage",
    "package_bugreports": "https://github.com/annahutch/corrcoverage/issues",
    "maintainer": "Anna Hutchinson <anna.hutchinson@mrc-bsu.cam.ac.uk>"
  },
  {
    "package": "covid19br",
    "on_cran": false,
    "archived_on": "2025-09-05 02:02:00",
    "url": "https://github.com/cranhaven/cranhaven.r-universe.dev",
    "branch": "package/covid19br",
    "subdir": "covid19br",
    "x_cran_comment_date": "2025-09-05",
    "x_cran_comment_event": "archived",
    "x_cran_comment_reason": "Repeated policy violation",
    "x_cran_history": "Archived on 2021-10-06 as email to the maintainer was undeliverable.\nUnarchived on 2021-10-08.\nArchived on 2023-02-22 for repeated policy violation.\n\nOn Internet access.\nUnarchived on 2023-05-08.\nArchived on 2023-09-01 for repeated policy violation.\n\nOn Internet access.\nUnarchived on 2023-09-05.\nArchived on 2023-09-06 as issues were still not corrected.\nUnarchived on 2023-10-15.\nArchived on 2025-05-19 for repeated policy violation.\n\nOn Internet access.\nUnarchived on 2025-08-19.",
    "package_url": "https://fndemarqui.github.io/covid19br/",
    "package_bugreports": "https://github.com/fndemarqui/covid19br/issues",
    "maintainer": "Fabio Demarqui <fndemarqui@est.ufmg.br>"
  },
  {
    "package": "CSGo",
    "on_cran": false,
    "archived_on": "2025-09-09 07:02:00",
    "url": "https://github.com/cranhaven/cranhaven.r-universe.dev",
    "branch": "package/CSGo",
    "subdir": "CSGo",
    "x_cran_comment_date": "2025-09-09",
    "x_cran_comment_event": "archived",
    "x_cran_comment_reason": "Requires archived package 'extrafont'",
    "package_url": "https://github.com/adsoncostanzifilho/CSGo",
    "package_bugreports": "https://github.com/adsoncostanzifilho/CSGo/issues",
    "maintainer": "Adson Costanzi <adsoncostanzi32@gmail.com>"
  },
  {
    "package": "cxreg",
    "on_cran": false,
    "archived_on": "2025-10-01 08:02:00",
    "url": "https://github.com/cranhaven/cranhaven.r-universe.dev",
    "branch": "package/cxreg",
    "subdir": "cxreg",
    "x_cran_comment_date": "2025-10-01",
    "x_cran_comment_event": "archived",
    "x_cran_comment_reason": "Check issues were not corrected in time",
    "maintainer": "Younghoon Kim <yk748@cornell.edu>"
  },
  {
    "package": "D2MCS",
    "on_cran": false,
    "archived_on": "2025-09-12 03:02:00",
    "url": "https://github.com/cranhaven/cranhaven.r-universe.dev",
    "branch": "package/D2MCS",
    "subdir": "D2MCS",
    "x_cran_comment_date": "2025-09-12",
    "x_cran_comment_event": "archived",
    "x_cran_comment_reason": "The maintainer's request",
    "package_url": "https://github.com/drordas/D2MCS",
    "package_bugreports": "https://github.com/drordas/D2MCS/issues",
    "maintainer": "Miguel Ferreiro-Díaz <miguel.ferreiro.diaz@gmail.com>"
  },
  {
    "package": "dafishr",
    "on_cran": false,
    "archived_on": "2025-10-02 10:02:00",
    "url": "https://github.com/cranhaven/cranhaven.r-universe.dev",
    "branch": "package/dafishr",
    "subdir": "dafishr",
    "x_cran_comment_date": "2025-10-02",
    "x_cran_comment_event": "archived",
    "x_cran_comment_reason": "The maintainer's request",
    "package_url": "https://github.com/CBMC-GCMP/dafishr,\nhttps://cbmc-gcmp.github.io/dafishr/",
    "package_bugreports": "https://github.com/CBMC-GCMP/dafishr/issues/",
    "maintainer": "Fabio Favoretto <fabio@gocmarineprogram.org>"
  },
  {
    "package": "DCSmooth",
    "on_cran": false,
    "archived_on": "2025-09-17 08:02:00",
    "url": "https://github.com/cranhaven/cranhaven.r-universe.dev",
    "branch": "package/DCSmooth",
    "subdir": "DCSmooth",
    "x_cran_comment_date": "2025-09-17",
    "x_cran_comment_event": "archived",
    "x_cran_comment_reason": "Email to the maintainer is undeliverable",
    "maintainer": "Bastian Schaefer <bastian.schaefer@uni-paderborn.de>"
  },
  {
    "package": "designmatch",
    "on_cran": false,
    "archived_on": "2025-09-11 02:02:00",
    "url": "https://github.com/cranhaven/cranhaven.r-universe.dev",
    "branch": "package/designmatch",
    "subdir": "designmatch",
    "x_cran_comment_date": "2025-09-11",
    "x_cran_comment_event": "archived",
    "x_cran_comment_reason": "Errors were not corrected in time",
    "maintainer": "Jose R. Zubizarreta <zubizarreta@hcp.med.harvard.edu>"
  },
  {
    "package": "edgemodelr",
    "on_cran": false,
    "archived_on": "2025-10-02 05:02:00",
    "url": "https://github.com/cranhaven/cranhaven.r-universe.dev",
    "branch": "package/edgemodelr",
    "subdir": "edgemodelr",
    "x_cran_comment_date": "2025-10-02",
    "x_cran_comment_event": "archived",
    "x_cran_comment_reason": "Repearted policy violation. Repeated submissions with platform-dependent code, incorrectly documented. Repeated submissions whilst one is under consideration,",
    "package_url": "https://github.com/PawanRamaMali/edgemodelr",
    "package_bugreports": "https://github.com/PawanRamaMali/edgemodelr/issues",
    "maintainer": "Pawan Rama Mali <prm@outlook.in>"
  },
  {
    "package": "ElevDistr",
    "on_cran": false,
    "archived_on": "2025-09-20 06:02:00",
    "url": "https://github.com/cranhaven/cranhaven.r-universe.dev",
    "branch": "package/ElevDistr",
    "subdir": "ElevDistr",
    "x_cran_comment_date": "2025-09-20",
    "x_cran_comment_event": "archived",
    "x_cran_comment_reason": "Errors were not corrected in time",
    "package_url": "https://github.com/LivioBaetscher/ElevDistr",
    "package_bugreports": "https://github.com/LivioBaetscher/ElevDistr/issues",
    "maintainer": "Livio Bätscher <livio_999@hotmail.com>"
  },
  {
    "package": "EstimateBreed",
    "on_cran": false,
    "archived_on": "2025-09-09 08:02:00",
    "url": "https://github.com/cranhaven/cranhaven.r-universe.dev",
    "branch": "package/EstimateBreed",
    "subdir": "EstimateBreed",
    "x_cran_comment_date": "2025-09-09",
    "x_cran_comment_event": "archived",
    "x_cran_comment_reason": "Requires archived package 'hrbrthemes'",
    "package_url": "https://github.com/willyanjnr/EstimateBreed",
    "maintainer": "Willyan Junior Adorian Bandeira <bandeira.wjab@gmail.com>"
  },
  {
    "package": "factset.protobuf.stachextensions",
    "on_cran": false,
    "archived_on": "2025-09-23 05:02:00",
    "url": "https://github.com/cranhaven/cranhaven.r-universe.dev",
    "branch": "package/factset.protobuf.stachextensions",
    "subdir": "factset.protobuf.stachextensions",
    "x_cran_comment_date": "2025-09-23",
    "x_cran_comment_event": "archived",
    "x_cran_comment_reason": "Check problems were not corrected despite reminders",
    "x_cran_history": "Archived on 2022-08-08 as issues were not corrected in time.\n\nSuggested package not used conditionally.\nUnarchived on 2023-01-12.",
    "package_url": "https://github.com/factset/stach-extensions",
    "package_bugreports": "https://github.com/factset/stach-extensions/issues",
    "maintainer": "Veda Bhaskara Ramanth <vedabhaskararamanth.addala@factset.com>"
  },
  {
    "package": "FamilyRank",
    "on_cran": false,
    "archived_on": "2025-09-17 08:02:00",
    "url": "https://github.com/cranhaven/cranhaven.r-universe.dev",
    "branch": "package/FamilyRank",
    "subdir": "FamilyRank",
    "x_cran_comment_date": "2025-09-17",
    "x_cran_comment_event": "archived",
    "x_cran_comment_reason": "Email to the maintainer is undeliverable",
    "maintainer": "Michelle Saul <msaul@carisls.com>"
  },
  {
    "package": "fctbases",
    "on_cran": false,
    "archived_on": "2025-09-17 08:02:00",
    "url": "https://github.com/cranhaven/cranhaven.r-universe.dev",
    "branch": "package/fctbases",
    "subdir": "fctbases",
    "x_cran_comment_date": "2025-09-17",
    "x_cran_comment_event": "archived",
    "x_cran_comment_reason": "Email to the maintainer is undeliverable",
    "x_cran_history": "Archived on 2022-01-28 as check problems were not corrected in time.\nUnarchived on 2022-05-17.",
    "package_url": "https://github.com/naolsen/fctbases",
    "maintainer": "Niels Olsen <nalo@dtu.dk>"
  },
  {
    "package": "fergm",
    "on_cran": false,
    "archived_on": "2025-09-09 07:02:00",
    "url": "https://github.com/cranhaven/cranhaven.r-universe.dev",
    "branch": "package/fergm",
    "subdir": "fergm",
    "x_cran_comment_date": "2025-09-09",
    "x_cran_comment_event": "archived",
    "x_cran_comment_reason": "Requires archived package 'extrafont'",
    "package_url": "http://github.com/benjamin-w-campbell/fergm",
    "maintainer": "Benjamin W. Campbell <campbell.1721@osu.edu>"
  },
  {
    "package": "fgdr",
    "on_cran": false,
    "archived_on": "2025-09-28 08:02:00",
    "url": "https://github.com/cranhaven/cranhaven.r-universe.dev",
    "branch": "package/fgdr",
    "subdir": "fgdr",
    "x_cran_comment_date": "2025-09-28",
    "x_cran_comment_event": "archived",
    "x_cran_comment_reason": "Check problems were not corrected despite reminders",
    "package_url": "https://github.com/uribo/fgdr",
    "package_bugreports": "https://github.com/uribo/fgdr/issues",
    "maintainer": "Shinya Uryu <suika1127@gmail.com>"
  },
  {
    "package": "figuRes2",
    "on_cran": false,
    "archived_on": "2025-10-01 08:02:00",
    "url": "https://github.com/cranhaven/cranhaven.r-universe.dev",
    "branch": "package/figuRes2",
    "subdir": "figuRes2",
    "x_cran_comment_date": "2025-10-01",
    "x_cran_comment_event": "archived",
    "x_cran_comment_reason": "Check issues were not corrected in time",
    "package_url": "https://github.com/gcicc/figures2",
    "maintainer": "Greg Cicconetti <greg.cicconetti@gmail.com>"
  },
  {
    "package": "FMCCSD",
    "on_cran": false,
    "archived_on": "2025-09-17 08:02:00",
    "url": "https://github.com/cranhaven/cranhaven.r-universe.dev",
    "branch": "package/FMCCSD",
    "subdir": "FMCCSD",
    "x_cran_comment_date": "2025-09-17",
    "x_cran_comment_event": "archived",
    "x_cran_comment_reason": "Email to the maintainer is undeliverable",
    "maintainer": "Tong Wang <tong@stat.tamu.edu>"
  },
  {
    "package": "ForecastTB",
    "on_cran": false,
    "archived_on": "2025-10-02 01:02:00",
    "url": "https://github.com/cranhaven/cranhaven.r-universe.dev",
    "branch": "package/ForecastTB",
    "subdir": "ForecastTB",
    "x_cran_comment_date": "2025-10-02",
    "x_cran_comment_event": "archived",
    "x_cran_comment_reason": "Check issues were not corrected in time",
    "maintainer": "Neeraj Dhanraj Bokde <neerajdhanraj@gmail.com>"
  },
  {
    "package": "forensIT",
    "on_cran": false,
    "archived_on": "2025-09-09 08:02:00",
    "url": "https://github.com/cranhaven/cranhaven.r-universe.dev",
    "branch": "package/forensIT",
    "subdir": "forensIT",
    "x_cran_comment_date": "2025-09-09",
    "x_cran_comment_event": "archived",
    "x_cran_comment_reason": "Requires archived package 'hrbrthemes'",
    "maintainer": "Franco Marsico <franco.lmarsico@gmail.com>"
  },
  {
    "package": "gamblers.ruin.gameplay",
    "on_cran": false,
    "archived_on": "2025-09-09 08:02:00",
    "url": "https://github.com/cranhaven/cranhaven.r-universe.dev",
    "branch": "package/gamblers.ruin.gameplay",
    "subdir": "gamblers.ruin.gameplay",
    "x_cran_comment_date": "2025-09-09",
    "x_cran_comment_event": "archived",
    "x_cran_comment_reason": "Requires archived package 'hrbrthemes'",
    "maintainer": "Somjit Roy <somjit.roy2001@gmail.com>"
  },
  {
    "package": "gfoRmulaICE",
    "on_cran": false,
    "archived_on": "2025-09-17 08:02:00",
    "url": "https://github.com/cranhaven/cranhaven.r-universe.dev",
    "branch": "package/gfoRmulaICE",
    "subdir": "gfoRmulaICE",
    "x_cran_comment_date": "2025-09-17",
    "x_cran_comment_event": "archived",
    "x_cran_comment_reason": "Email to the maintainer is undeliverable",
    "maintainer": "Zhaoxi Cheng <zcheng@hsph.harvard.edu>"
  },
  {
    "package": "ggedit",
    "on_cran": false,
    "archived_on": "2025-09-08 14:02:00",
    "url": "https://github.com/cranhaven/cranhaven.r-universe.dev",
    "branch": "package/ggedit",
    "subdir": "ggedit",
    "x_cran_comment_date": "2025-09-08",
    "x_cran_comment_event": "archived",
    "x_cran_comment_reason": "The maintainer's request",
    "package_url": "https://github.com/yonicd/ggedit",
    "package_bugreports": "https://github.com/yonicd/ggedit/issues",
    "maintainer": "Jonathan Sidi <yonicd@gmail.com>"
  },
  {
    "package": "glmtree",
    "on_cran": false,
    "archived_on": "2025-10-03 01:02:00",
    "url": "https://github.com/cranhaven/cranhaven.r-universe.dev",
    "branch": "package/glmtree",
    "subdir": "glmtree",
    "x_cran_comment_date": "2025-10-03",
    "x_cran_comment_event": "archived",
    "x_cran_comment_reason": "Check issues were not corrected in time",
    "package_url": "https://adimajo.github.io",
    "package_bugreports": "https://github.com/adimajo/glmtree/issues",
    "maintainer": "Adrien Ehrhardt <adrien.ehrhardt@centraliens-lille.org>"
  },
  {
    "package": "greta",
    "on_cran": false,
    "archived_on": "2025-09-20 06:02:00",
    "url": "https://github.com/cranhaven/cranhaven.r-universe.dev",
    "branch": "package/greta",
    "subdir": "greta",
    "x_cran_comment_date": "2025-09-20",
    "x_cran_comment_event": "archived",
    "x_cran_comment_reason": "Errors were not corrected despite reminders",
    "package_url": "https://greta-stats.org, https://github.com/greta-dev/greta",
    "package_bugreports": "https://github.com/greta-dev/greta/issues",
    "maintainer": "Nicholas Tierney <nicholas.tierney@gmail.com>"
  },
  {
    "package": "greta.censored",
    "on_cran": false,
    "archived_on": "2025-09-20 06:02:00",
    "url": "https://github.com/cranhaven/cranhaven.r-universe.dev",
    "branch": "package/greta.censored",
    "subdir": "greta.censored",
    "x_cran_comment_date": "2025-09-20",
    "x_cran_comment_event": "archived",
    "x_cran_comment_reason": "Requires archived package 'greta'",
    "package_url": "https://github.com/mtwesley/greta.censored",
    "package_bugreports": "https://github.com/mtwesley/greta.censored/issues",
    "maintainer": "Mlen-Too Wesley <mlen.too.wesley@gmail.com>"
  },
  {
    "package": "greta.dynamics",
    "on_cran": false,
    "archived_on": "2025-09-20 06:02:00",
    "url": "https://github.com/cranhaven/cranhaven.r-universe.dev",
    "branch": "package/greta.dynamics",
    "subdir": "greta.dynamics",
    "x_cran_comment_date": "2025-09-20",
    "x_cran_comment_event": "archived",
    "x_cran_comment_reason": "Requires archived package 'greta'",
    "package_url": "https://github.com/greta-dev/greta.dynamics,\nhttps://greta-dev.github.io/greta.dynamics/",
    "package_bugreports": "https://github.com/greta-dev/greta.dynamics/issues",
    "maintainer": "Nicholas Tierney <nicholas.tierney@gmail.com>"
  },
  {
    "package": "greta.gam",
    "on_cran": false,
    "archived_on": "2025-09-20 06:02:00",
    "url": "https://github.com/cranhaven/cranhaven.r-universe.dev",
    "branch": "package/greta.gam",
    "subdir": "greta.gam",
    "x_cran_comment_date": "2025-09-20",
    "x_cran_comment_event": "archived",
    "x_cran_comment_reason": "Requires archived package 'greta'",
    "package_url": "https://github.com/greta-dev/greta.gam,\nhttps://greta-dev.github.io/greta.gam/",
    "package_bugreports": "https://github.com/greta-dev/greta.gam/issues",
    "maintainer": "Nicholas Tierney <nicholas.tierney@gmail.com>"
  },
  {
    "package": "greta.gp",
    "on_cran": false,
    "archived_on": "2025-09-20 06:02:00",
    "url": "https://github.com/cranhaven/cranhaven.r-universe.dev",
    "branch": "package/greta.gp",
    "subdir": "greta.gp",
    "x_cran_comment_date": "2025-09-20",
    "x_cran_comment_event": "archived",
    "x_cran_comment_reason": "Requires archived package 'greta'",
    "package_url": "https://github.com/greta-dev/greta.gp,\nhttps://greta-dev.github.io/greta.gp/",
    "package_bugreports": "https://github.com/greta-dev/greta.gp/issues",
    "maintainer": "Nicholas Tierney <nicholas.tierney@gmail.com>"
  },
  {
    "package": "GTFSwizard",
    "on_cran": false,
    "archived_on": "2025-09-09 08:02:00",
    "url": "https://github.com/cranhaven/cranhaven.r-universe.dev",
    "branch": "package/GTFSwizard",
    "subdir": "GTFSwizard",
    "x_cran_comment_date": "2025-09-09",
    "x_cran_comment_event": "archived",
    "x_cran_comment_reason": "Requires archived package 'hrbrthemes'",
    "package_url": "https://github.com/OPATP/GTFSwizard",
    "package_bugreports": "https://github.com/OPATP/GTFSwizard/issues",
    "maintainer": "Nelson de O. Quesado Filho <nquesado@gmail.com>"
  },
  {
    "package": "hdbm",
    "on_cran": false,
    "archived_on": "2025-09-17 08:02:00",
    "url": "https://github.com/cranhaven/cranhaven.r-universe.dev",
    "branch": "package/hdbm",
    "subdir": "hdbm",
    "x_cran_comment_date": "2025-09-17",
    "x_cran_comment_event": "archived",
    "x_cran_comment_reason": "Email to the maintainer is undeliverable",
    "maintainer": "Alexander Rix <alexrix@umich.edu>"
  },
  {
    "package": "hdtg",
    "on_cran": false,
    "archived_on": "2025-09-15 07:02:00",
    "url": "https://github.com/cranhaven/cranhaven.r-universe.dev",
    "branch": "package/hdtg",
    "subdir": "hdtg",
    "x_cran_comment_date": "2025-09-15",
    "x_cran_comment_event": "archived",
    "x_cran_comment_reason": "Errors were not corrected in time",
    "x_cran_history": "Archived on 2023-05-01 as issues were not corrected in time.\nUnarchived on 2025-05-20.",
    "maintainer": "Zhenyu Zhang <zhangzhenyusa@gmail.com>"
  },
  {
    "package": "HMB",
    "on_cran": false,
    "archived_on": "2025-09-17 08:02:00",
    "url": "https://github.com/cranhaven/cranhaven.r-universe.dev",
    "branch": "package/HMB",
    "subdir": "HMB",
    "x_cran_comment_date": "2025-09-17",
    "x_cran_comment_event": "archived",
    "x_cran_comment_reason": "Email to the maintainer is undeliverable",
    "maintainer": "Svetlana Saarela <admin@svetlanasaarela.com>"
  },
  {
    "package": "hrbrthemes",
    "on_cran": false,
    "archived_on": "2025-09-09 07:02:00",
    "url": "https://github.com/cranhaven/cranhaven.r-universe.dev",
    "branch": "package/hrbrthemes",
    "subdir": "hrbrthemes",
    "x_cran_comment_date": "2025-09-09",
    "x_cran_comment_event": "archived",
    "x_cran_comment_reason": "Requires archived package 'extrafont'",
    "x_cran_history": "Orphaned and corrected on 2018-08-19 as check problems were not corrected despite reminders.\nUnarchived on 2019-01-21.",
    "maintainer": "Bob Rudis <bob@rud.is>"
  },
  {
    "package": "ILSE",
    "on_cran": false,
    "archived_on": "2025-09-17 08:02:00",
    "url": "https://github.com/cranhaven/cranhaven.r-universe.dev",
    "branch": "package/ILSE",
    "subdir": "ILSE",
    "x_cran_comment_date": "2025-09-17",
    "x_cran_comment_event": "archived",
    "x_cran_comment_reason": "Email to the maintainer is undeliverable",
    "package_url": "https://github.com/feiyoung/ILSE",
    "package_bugreports": "https://github.com/feiyoung/ILSE/issues",
    "maintainer": "Wei Liu <weiliu@smail.swufe.edu.cn>"
  },
  {
    "package": "implicitMeasures",
    "on_cran": false,
    "archived_on": "2025-09-07 03:02:00",
    "url": "https://github.com/cranhaven/cranhaven.r-universe.dev",
    "branch": "package/implicitMeasures",
    "subdir": "implicitMeasures",
    "x_cran_comment_date": "2025-09-07",
    "x_cran_comment_event": "archived",
    "x_cran_comment_reason": "Errors were not corrected in time",
    "maintainer": "Ottavia M. Epifania <otta.epifania@gmail.com>"
  },
  {
    "package": "influxdbclient",
    "on_cran": false,
    "archived_on": "2025-09-23 05:02:00",
    "url": "https://github.com/cranhaven/cranhaven.r-universe.dev",
    "branch": "package/influxdbclient",
    "subdir": "influxdbclient",
    "x_cran_comment_date": "2025-09-23",
    "x_cran_comment_event": "archived",
    "x_cran_comment_reason": "Check problems were not corrected despite reminders",
    "package_url": "https://github.com/influxdata/influxdb-client-r",
    "package_bugreports": "https://github.com/influxdata/influxdb-client-r/issues",
    "maintainer": "Ales Pour <ales.pour@bonitoo.io>"
  },
  {
    "package": "jstor",
    "on_cran": false,
    "archived_on": "2025-09-28 08:02:00",
    "url": "https://github.com/cranhaven/cranhaven.r-universe.dev",
    "branch": "package/jstor",
    "subdir": "jstor",
    "x_cran_comment_date": "2025-09-28",
    "x_cran_comment_event": "archived",
    "x_cran_comment_reason": "Check problems were not corrected despite reminders",
    "x_cran_history": "Archived on 2018-07-15 for policy violation.\n\nLeaves two '.csv' files in '/tmp'.\nUnarchived on 2018-07-20.\nArchived on 2021-08-04 as check problems were not corrected in time.\nUnarchived on 2021-12-08.",
    "package_url": "https://github.com/ropensci/jstor,\nhttps://docs.ropensci.org/jstor/",
    "package_bugreports": "https://github.com/ropensci/jstor/issues",
    "maintainer": "Thomas Klebel <t.klebel@hotmail.com>"
  },
  {
    "package": "lazyWeave",
    "on_cran": false,
    "archived_on": "2025-09-26 03:02:00",
    "url": "https://github.com/cranhaven/cranhaven.r-universe.dev",
    "branch": "package/lazyWeave",
    "subdir": "lazyWeave",
    "x_cran_comment_date": "2025-09-26",
    "x_cran_comment_event": "archived",
    "x_cran_comment_reason": "The maintainer's request",
    "x_cran_history": "Archived on 2015-07-01 as maintainer address bounced.",
    "maintainer": "Benjamin Nutter <benjamin.nutter@gmail.com>"
  },
  {
    "package": "linconGaussR",
    "on_cran": false,
    "archived_on": "2025-09-17 08:02:00",
    "url": "https://github.com/cranhaven/cranhaven.r-universe.dev",
    "branch": "package/linconGaussR",
    "subdir": "linconGaussR",
    "x_cran_comment_date": "2025-09-17",
    "x_cran_comment_event": "archived",
    "x_cran_comment_reason": "Email to the maintainer is undeliverable",
    "package_url": "https://github.com/YunyiShen/linconGaussR",
    "package_bugreports": "https://github.com/YunyiShen/linconGaussR/issues",
    "maintainer": "Yunyi Shen <yshen99@wisc.edu>"
  },
  {
    "package": "lodr",
    "on_cran": false,
    "archived_on": "2025-09-17 08:02:00",
    "url": "https://github.com/cranhaven/cranhaven.r-universe.dev",
    "branch": "package/lodr",
    "subdir": "lodr",
    "x_cran_comment_date": "2025-09-17",
    "x_cran_comment_event": "archived",
    "x_cran_comment_reason": "Email to the maintainer is undeliverable",
    "maintainer": "Kevin Donovan <kmdono02@ad.unc.edu>"
  },
  {
    "package": "MAPITR",
    "on_cran": false,
    "archived_on": "2025-09-17 08:02:00",
    "url": "https://github.com/cranhaven/cranhaven.r-universe.dev",
    "branch": "package/MAPITR",
    "subdir": "MAPITR",
    "x_cran_comment_date": "2025-09-17",
    "x_cran_comment_event": "archived",
    "x_cran_comment_reason": "Email to the maintainer is undeliverable",
    "package_url": "https://github.com/mturchin20/MAPITR",
    "package_bugreports": "https://github.com/mturchin20/MAPITR/issues",
    "maintainer": "Michael Turchin <michael_turchin@brown.edu>"
  },
  {
    "package": "meshed",
    "on_cran": false,
    "archived_on": "2025-09-17 08:02:00",
    "url": "https://github.com/cranhaven/cranhaven.r-universe.dev",
    "branch": "package/meshed",
    "subdir": "meshed",
    "x_cran_comment_date": "2025-09-17",
    "x_cran_comment_event": "archived",
    "x_cran_comment_reason": "Email to the maintainer is undeliverable",
    "maintainer": "Michele Peruzzi <michele.peruzzi@duke.edu>"
  },
  {
    "package": "MLVSBM",
    "on_cran": false,
    "archived_on": "2025-09-23 05:02:00",
    "url": "https://github.com/cranhaven/cranhaven.r-universe.dev",
    "branch": "package/MLVSBM",
    "subdir": "MLVSBM",
    "x_cran_comment_date": "2025-09-23",
    "x_cran_comment_event": "archived",
    "x_cran_comment_reason": "Check problems were not corrected despite reminders",
    "x_cran_history": "Archived on 2022-04-20 as check issues were not corrected in time.\nUnarchived on 2022-08-05.",
    "package_url": "https://github.com/Chabert-Liddell/MLVSBM",
    "package_bugreports": "https://github.com/Chabert-Liddell/MLVSBM/issues",
    "maintainer": "Saint-Clair Chabert-Liddell <academic@chabert-liddell.com>"
  },
  {
    "package": "mnreadR",
    "on_cran": false,
    "archived_on": "2025-10-01 08:02:00",
    "url": "https://github.com/cranhaven/cranhaven.r-universe.dev",
    "branch": "package/mnreadR",
    "subdir": "mnreadR",
    "x_cran_comment_date": "2025-10-01",
    "x_cran_comment_event": "archived",
    "x_cran_comment_reason": "Check issues were not corrected in time",
    "x_cran_history": "Archived on 2023-08-19 as email to the maintainer is undeliverable.\nUnarchived on 2024-01-18.",
    "package_url": "https://legge.psych.umn.edu/mnread-acuity-charts",
    "maintainer": "Aurélie Calabrèse <aurelie.calabrese@univ-amu.fr>"
  },
  {
    "package": "mrgdp",
    "on_cran": false,
    "archived_on": "2025-10-01 08:02:00",
    "url": "https://github.com/cranhaven/cranhaven.r-universe.dev",
    "branch": "package/mrgdp",
    "subdir": "mrgdp",
    "x_cran_comment_date": "2025-10-01",
    "x_cran_comment_event": "archived",
    "x_cran_comment_reason": "Policy violation. On Internet access",
    "package_url": "<https://github.com/MarcoAPerezM/mrgdp>,\nhttps://github.com/MarcoAPerezM/mrgdp",
    "package_bugreports": "https://github.com/MarcoAPerezM/mrgdp/issues",
    "maintainer": "Marco Antonio Pérez-Méndez <mperez.mendez@izt.uam.mx>"
  },
  {
    "package": "mstrio",
    "on_cran": false,
    "archived_on": "2025-09-23 05:02:00",
    "url": "https://github.com/cranhaven/cranhaven.r-universe.dev",
    "branch": "package/mstrio",
    "subdir": "mstrio",
    "x_cran_comment_date": "2025-09-23",
    "x_cran_comment_event": "archived",
    "x_cran_comment_reason": "Check problems were not corrected despite reminders",
    "x_cran_history": "Archived on 2018-09-10 for policy violation.\n\nRunning the vignettes requires availability of a web service which was\nonly made available for getting the package published on CRAN.\nUnarchived on 2018-09-14.",
    "maintainer": "Piotr Kowal <pkowal@microstrategy.com>"
  },
  {
    "package": "multilevelcoda",
    "on_cran": false,
    "archived_on": "2025-09-09 08:02:00",
    "url": "https://github.com/cranhaven/cranhaven.r-universe.dev",
    "branch": "package/multilevelcoda",
    "subdir": "multilevelcoda",
    "x_cran_comment_date": "2025-09-09",
    "x_cran_comment_event": "archived",
    "x_cran_comment_reason": "Requires archived package 'hrbrthemes'",
    "x_cran_history": "Archived on 2023-06-09 as issues were not corrected in time.\nUnarchived on 2023-06-16.\nArchived on 2024-02-29 as issues were not corrected in time.\nUnarchived on 2024-03-10.\nArchived on 2024-04-04 as issues were not corrected in time.\nUnarchived on 2024-06-11.",
    "package_url": "https://florale.github.io/multilevelcoda/,\nhttps://github.com/florale/multilevelcoda",
    "package_bugreports": "https://github.com/florale/multilevelcoda/issues",
    "maintainer": "Flora Le <floralebui@gmail.com>"
  },
  {
    "package": "netcmc",
    "on_cran": false,
    "archived_on": "2025-09-17 09:02:00",
    "url": "https://github.com/cranhaven/cranhaven.r-universe.dev",
    "branch": "package/netcmc",
    "subdir": "netcmc",
    "x_cran_comment_date": "2025-09-17",
    "x_cran_comment_event": "archived",
    "x_cran_comment_reason": "Email to the maintainer is undeliverable",
    "maintainer": "George Gerogiannis <g.gerogiannis.1@research.gla.ac.uk>"
  },
  {
    "package": "oesr",
    "on_cran": false,
    "archived_on": "2025-09-09 07:02:00",
    "url": "https://github.com/cranhaven/cranhaven.r-universe.dev",
    "branch": "package/oesr",
    "subdir": "oesr",
    "x_cran_comment_date": "2025-09-09",
    "x_cran_comment_event": "archived",
    "x_cran_comment_reason": "Requires archived package 'extrafont'",
    "maintainer": "Ryan T. Moore <ryan.moore@gsa.gov>"
  },
  {
    "package": "openaistream",
    "on_cran": false,
    "archived_on": "2025-09-23 05:02:00",
    "url": "https://github.com/cranhaven/cranhaven.r-universe.dev",
    "branch": "package/openaistream",
    "subdir": "openaistream",
    "x_cran_comment_date": "2025-09-23",
    "x_cran_comment_event": "archived",
    "x_cran_comment_reason": "Check problems were not corrected despite reminders",
    "package_url": "https://github.com/libingfei/openaistream",
    "package_bugreports": "https://github.com/libingfei/openaistream/issues",
    "maintainer": "Li Gen <libingfei@sina.com>"
  },
  {
    "package": "pathwayTMB",
    "on_cran": false,
    "archived_on": "2025-09-21 01:02:00",
    "url": "https://github.com/cranhaven/cranhaven.r-universe.dev",
    "branch": "package/pathwayTMB",
    "subdir": "pathwayTMB",
    "x_cran_comment_date": "2025-09-20",
    "x_cran_comment_event": "archived",
    "x_cran_comment_reason": "Errors were not corrected in time",
    "x_cran_history": "Archived on 2022-05-07 as calls defunct 'default.stringsAsFactors()'\nUnarchived on 2022-05-18.",
    "maintainer": "Junwei Han <hanjunwei1981@163.com>"
  },
  {
    "package": "PLStests",
    "on_cran": false,
    "archived_on": "2025-09-02 06:02:00",
    "url": "https://github.com/cranhaven/cranhaven.r-universe.dev",
    "branch": "package/PLStests",
    "subdir": "PLStests",
    "x_cran_comment_date": "2025-09-02",
    "x_cran_comment_event": "archived",
    "x_cran_comment_reason": "The maintainer's request",
    "maintainer": "Wen Chen <tlqdcw@gmail.com>"
  },
  {
    "package": "PopPsiSeqR",
    "on_cran": false,
    "archived_on": "2025-10-02 01:02:00",
    "url": "https://github.com/cranhaven/cranhaven.r-universe.dev",
    "branch": "package/PopPsiSeqR",
    "subdir": "PopPsiSeqR",
    "x_cran_comment_date": "2025-10-02",
    "x_cran_comment_event": "archived",
    "x_cran_comment_reason": "Check issues were not corrected in time",
    "package_url": "https://github.com/csoeder/PopPsiSeq,\nhttps://github.com/csoeder/PopPsiSeqR",
    "package_bugreports": "https://github.com/csoeder/PopPsiSeqR/issues",
    "maintainer": "Charles Soeder <csoeder@email.unc.edu>"
  },
  {
    "package": "ProgModule",
    "on_cran": false,
    "archived_on": "2025-09-21 01:02:00",
    "url": "https://github.com/cranhaven/cranhaven.r-universe.dev",
    "branch": "package/ProgModule",
    "subdir": "ProgModule",
    "x_cran_comment_date": "2025-09-20",
    "x_cran_comment_event": "archived",
    "x_cran_comment_reason": "Requires archived package 'pathwayTMB'",
    "maintainer": "Junwei Han <hanjunwei1981@163.com>"
  },
  {
    "package": "psc",
    "on_cran": false,
    "archived_on": "2025-09-09 08:02:00",
    "url": "https://github.com/cranhaven/cranhaven.r-universe.dev",
    "branch": "package/psc",
    "subdir": "psc",
    "x_cran_comment_date": "2025-09-09",
    "x_cran_comment_event": "archived",
    "x_cran_comment_reason": "Requires archived package 'waffle'",
    "package_url": "https://github.com/richjjackson/psc/,\nhttps://github.com/richJJackson/psc",
    "package_bugreports": "https://github.com/richJJackson/psc/issues",
    "maintainer": "Richard Jackson <richJ23@liverpool.ac.uk>"
  },
  {
    "package": "ratlas",
    "on_cran": false,
    "archived_on": "2025-09-09 07:02:00",
    "url": "https://github.com/cranhaven/cranhaven.r-universe.dev",
    "branch": "package/ratlas",
    "subdir": "ratlas",
    "x_cran_comment_date": "2025-09-09",
    "x_cran_comment_event": "archived",
    "x_cran_comment_reason": "Requires archived package 'extrafont'",
    "package_url": "https://ratlas.netlify.app, https://github.com/atlas-aai/ratlas",
    "package_bugreports": "https://github.com/atlas-aai/ratlas/issues",
    "maintainer": "W. Jake Thompson <wjakethompson@gmail.com>"
  },
  {
    "package": "RCreliability",
    "on_cran": false,
    "archived_on": "2025-09-05 12:02:00",
    "url": "https://github.com/cranhaven/cranhaven.r-universe.dev",
    "branch": "package/RCreliability",
    "subdir": "RCreliability",
    "x_cran_comment_date": "2025-09-05",
    "x_cran_comment_event": "archived",
    "x_cran_comment_reason": "The maintainer's request",
    "maintainer": "Yu Lu <yulu@hsph.harvard.edu>"
  },
  {
    "package": "repo.data",
    "on_cran": false,
    "archived_on": "2025-10-01 08:02:00",
    "url": "https://github.com/cranhaven/cranhaven.r-universe.dev",
    "branch": "package/repo.data",
    "subdir": "repo.data",
    "x_cran_comment_date": "2025-10-01",
    "x_cran_comment_event": "archived",
    "x_cran_comment_reason": "Policy violation. On Internet access",
    "package_url": "https://github.com/llrs/repo.data,\nhttps://llrs.github.io/repo.data/",
    "package_bugreports": "https://github.com/llrs/repo.data/issues",
    "maintainer": "Lluís Revilla Sancho <lluis.revilla@gmail.com>"
  },
  {
    "package": "rlibkriging",
    "on_cran": false,
    "archived_on": "2025-09-18 02:02:00",
    "url": "https://github.com/cranhaven/cranhaven.r-universe.dev",
    "branch": "package/rlibkriging",
    "subdir": "rlibkriging",
    "x_cran_comment_date": "2025-09-18",
    "x_cran_comment_event": "archived",
    "x_cran_comment_reason": "Errors were not corrected in time",
    "x_cran_history": "Archived on 2022-10-06 as installation issues were not corrected in time.\nUnarchived on 2023-01-06.\nArchived on 2023-09-28 as check issues were not corrected in re-submission.\n\nAnd policy violation: spamming email address of a team member.\nUnarchived on 2023-11-28.\nArchived on 2025-01-10 as issues were not corrected in time.\nGCC 15: outdated 'armadillo' included.\nUnarchived on 2025-01-15.\nArchived on 2025-06-16 as issues were not corrected in time.\nUnarchived on 2025-07-22.\nArchived on 2025-08-25 as errors were not corrected in time.\nUnarchived on 2025-08-27.",
    "package_url": "https://github.com/libKriging",
    "maintainer": "Yann Richet <yann.richet@asnr.fr>"
  },
  {
    "package": "rminizinc",
    "on_cran": false,
    "archived_on": "2025-09-23 05:02:00",
    "url": "https://github.com/cranhaven/cranhaven.r-universe.dev",
    "branch": "package/rminizinc",
    "subdir": "rminizinc",
    "x_cran_comment_date": "2025-09-23",
    "x_cran_comment_event": "archived",
    "x_cran_comment_reason": "Check problems were not corrected despite reminders",
    "package_url": "https://github.com/acharaakshit/RMiniZinc",
    "package_bugreports": "https://github.com/acharaakshit/RMiniZinc/issues",
    "maintainer": "Akshit Achara <acharaakshit@gmail.com>"
  },
  {
    "package": "robustcov",
    "on_cran": false,
    "archived_on": "2025-09-17 09:02:00",
    "url": "https://github.com/cranhaven/cranhaven.r-universe.dev",
    "branch": "package/robustcov",
    "subdir": "robustcov",
    "x_cran_comment_date": "2025-09-17",
    "x_cran_comment_event": "archived",
    "x_cran_comment_reason": "Email to the maintainer is undeliverable",
    "maintainer": "Yunyi Shen <yshen99@wisc.edu>"
  },
  {
    "package": "rocTree",
    "on_cran": false,
    "archived_on": "2025-09-17 09:02:00",
    "url": "https://github.com/cranhaven/cranhaven.r-universe.dev",
    "branch": "package/rocTree",
    "subdir": "rocTree",
    "x_cran_comment_date": "2025-09-17",
    "x_cran_comment_event": "archived",
    "x_cran_comment_reason": "Email to the maintainer is undeliverable",
    "x_cran_history": "Archived on 2019-11-27 as installation failure was not corrected despite reminder.\nUnarchived on 2020-08-01.",
    "package_url": "http://github.com/stc04003/rocTree",
    "package_bugreports": "http://github.com/stc04003/rocTree/issues",
    "maintainer": "Sy Han Chiou <schiou@utdallas.edu>"
  },
  {
    "package": "RVenn",
    "on_cran": false,
    "archived_on": "2025-09-05 11:02:00",
    "url": "https://github.com/cranhaven/cranhaven.r-universe.dev",
    "branch": "package/RVenn",
    "subdir": "RVenn",
    "x_cran_comment_date": "2025-09-05",
    "x_cran_comment_event": "archived",
    "x_cran_comment_reason": "The maintainer's request",
    "maintainer": "Turgut Yigit Akyol <tyakyol@gmail.com>"
  },
  {
    "package": "schtools",
    "on_cran": false,
    "archived_on": "2025-09-23 03:02:00",
    "url": "https://github.com/cranhaven/cranhaven.r-universe.dev",
    "branch": "package/schtools",
    "subdir": "schtools",
    "x_cran_comment_date": "2025-09-22",
    "x_cran_comment_event": "archived",
    "x_cran_comment_reason": "Errors were not corrected in time",
    "package_url": "http://www.schlosslab.org/schtools/,\nhttps://github.com/SchlossLab/schtools",
    "package_bugreports": "https://github.com/SchlossLab/schtools/issues",
    "maintainer": "Kelly Sovacool <sovacool@umich.edu>"
  },
  {
    "package": "seedreg",
    "on_cran": false,
    "archived_on": "2025-09-17 09:02:00",
    "url": "https://github.com/cranhaven/cranhaven.r-universe.dev",
    "branch": "package/seedreg",
    "subdir": "seedreg",
    "x_cran_comment_date": "2025-09-17",
    "x_cran_comment_event": "archived",
    "x_cran_comment_reason": "Email to the maintainer is undeliverable",
    "maintainer": "Gabriel Danilo Shimizu <shimizu@uel.br>"
  },
  {
    "package": "SeqExpMatch",
    "on_cran": false,
    "archived_on": "2025-09-23 05:02:00",
    "url": "https://github.com/cranhaven/cranhaven.r-universe.dev",
    "branch": "package/SeqExpMatch",
    "subdir": "SeqExpMatch",
    "x_cran_comment_date": "2025-09-23",
    "x_cran_comment_event": "archived",
    "x_cran_comment_reason": "Check problems were not corrected despite reminders",
    "package_url": "https://github.com/kapelner/matching_on_the_fly_designs_R_package_and_paper_repr",
    "maintainer": "Adam Kapelner <kapelner@qc.cuny.edu>"
  },
  {
    "package": "shinyreforms",
    "on_cran": false,
    "archived_on": "2025-09-23 05:02:00",
    "url": "https://github.com/cranhaven/cranhaven.r-universe.dev",
    "branch": "package/shinyreforms",
    "subdir": "shinyreforms",
    "x_cran_comment_date": "2025-09-23",
    "x_cran_comment_event": "archived",
    "x_cran_comment_reason": "Check problems were not corrected despite reminders",
    "package_url": "https://github.com/piotrbajger/shinyreforms",
    "package_bugreports": "https://github.com/piotrbajger/shinyreforms",
    "maintainer": "Piotr Bajger <piotr.bajger@hotmail.com>"
  },
  {
    "package": "SouthKoreAPIs",
    "on_cran": false,
    "archived_on": "2025-10-01 08:02:00",
    "url": "https://github.com/cranhaven/cranhaven.r-universe.dev",
    "branch": "package/SouthKoreAPIs",
    "subdir": "SouthKoreAPIs",
    "x_cran_comment_date": "2025-10-01",
    "x_cran_comment_event": "archived",
    "x_cran_comment_reason": "Policy violation. On Internet access",
    "package_url": "https://github.com/lightbluetitan/southkoreapis,\nhttps://lightbluetitan.github.io/southkoreapis/",
    "package_bugreports": "https://github.com/lightbluetitan/southkoreapis/issues",
    "maintainer": "Renzo Caceres Rossi <arenzocaceresrossi@gmail.com>"
  },
  {
    "package": "spreadr",
    "on_cran": false,
    "archived_on": "2025-09-09 07:02:00",
    "url": "https://github.com/cranhaven/cranhaven.r-universe.dev",
    "branch": "package/spreadr",
    "subdir": "spreadr",
    "x_cran_comment_date": "2025-09-09",
    "x_cran_comment_event": "archived",
    "x_cran_comment_reason": "Requires archived package 'extrafont'",
    "maintainer": "Cynthia Siew <cynsiewsq@gmail.com>"
  },
  {
    "package": "sssc",
    "on_cran": false,
    "archived_on": "2025-09-17 09:02:00",
    "url": "https://github.com/cranhaven/cranhaven.r-universe.dev",
    "branch": "package/sssc",
    "subdir": "sssc",
    "x_cran_comment_date": "2025-09-17",
    "x_cran_comment_event": "archived",
    "x_cran_comment_reason": "Email to the maintainer is undeliverable",
    "maintainer": "Tao Jiang <tjiang8@ncsu.edu>"
  },
  {
    "package": "survivalAnalysis",
    "on_cran": false,
    "archived_on": "2025-09-09 08:02:00",
    "url": "https://github.com/cranhaven/cranhaven.r-universe.dev",
    "branch": "package/survivalAnalysis",
    "subdir": "survivalAnalysis",
    "x_cran_comment_date": "2025-09-09",
    "x_cran_comment_event": "archived",
    "x_cran_comment_reason": "Requires archived package 'tidytidbits'",
    "x_cran_history": "Archived on 2019-02-12 as check problems were not corrected in time.\nUnarchived on 2019-02-13.\nArchived on 2020-12-03 as depends on archived package 'tidytidbits'.\nUnarchived on 2021-04-24.",
    "maintainer": "Marcel Wiesweg <marcel.wiesweg@uk-essen.de>"
  },
  {
    "package": "telefit",
    "on_cran": false,
    "archived_on": "2025-09-17 09:02:00",
    "url": "https://github.com/cranhaven/cranhaven.r-universe.dev",
    "branch": "package/telefit",
    "subdir": "telefit",
    "x_cran_comment_date": "2025-09-17",
    "x_cran_comment_event": "archived",
    "x_cran_comment_reason": "Email to the maintainer is undeliverable",
    "x_cran_history": "Archived on 2019-02-08 as installation errors were not corrected despite reminder.\n\nMisuse of _C, assigning variables to themselves.\nAlso check failure with MKL.\nUnarchived on 2019-02-18.",
    "maintainer": "Joshua Hewitt <joshua.hewitt@duke.edu>"
  },
  {
    "package": "tidytidbits",
    "on_cran": false,
    "archived_on": "2025-09-09 07:02:00",
    "url": "https://github.com/cranhaven/cranhaven.r-universe.dev",
    "branch": "package/tidytidbits",
    "subdir": "tidytidbits",
    "x_cran_comment_date": "2025-09-09",
    "x_cran_comment_event": "archived",
    "x_cran_comment_reason": "Requires archived package 'extrafont'",
    "x_cran_history": "Archived on 2020-12-03 as check problems were not corrected in time.\nUnarchived on 2021-03-08.",
    "maintainer": "Marcel Wiesweg <marcel.wiesweg@uk-essen.de>"
  },
  {
    "package": "treenomial",
    "on_cran": false,
    "archived_on": "2025-09-17 09:02:00",
    "url": "https://github.com/cranhaven/cranhaven.r-universe.dev",
    "branch": "package/treenomial",
    "subdir": "treenomial",
    "x_cran_comment_date": "2025-09-17",
    "x_cran_comment_event": "archived",
    "x_cran_comment_reason": "Email to the maintainer is undeliverable",
    "package_url": "https://github.com/gouldmatt/treenomial",
    "maintainer": "Matthew Gould <mgould@sfu.ca>"
  },
  {
    "package": "tvthemes",
    "on_cran": false,
    "archived_on": "2025-09-09 07:02:00",
    "url": "https://github.com/cranhaven/cranhaven.r-universe.dev",
    "branch": "package/tvthemes",
    "subdir": "tvthemes",
    "x_cran_comment_date": "2025-09-09",
    "x_cran_comment_event": "archived",
    "x_cran_comment_reason": "Requires archived package 'extrafont'",
    "package_url": "https://github.com/Ryo-N7/tvthemes",
    "package_bugreports": "https://github.com/Ryo-N7/tvthemes/issues",
    "maintainer": "Ryo Nakagawara <ryonakagawara@gmail.com>"
  },
  {
    "package": "umx",
    "on_cran": false,
    "archived_on": "2025-09-09 08:02:00",
    "url": "https://github.com/cranhaven/cranhaven.r-universe.dev",
    "branch": "package/umx",
    "subdir": "umx",
    "x_cran_comment_date": "2025-09-09",
    "x_cran_comment_event": "archived",
    "x_cran_comment_reason": "Requires archived package 'hrbrthemes'",
    "x_cran_history": "Archived on 2018-01-25 for policy violation (leaving processes running).\nUnarchived on 2018-02-14.\nArchived on 2021-05-27 as check problems were not corrected in time.\nUnarchived on 2021-05-31.\nArchived on 2023-11-14 as issues were not corrected in time.\nUnarchived on 2023-11-16.",
    "package_url": "https://github.com/tbates/umx#readme",
    "package_bugreports": "https://github.com/tbates/umx/issues",
    "maintainer": "Timothy C. Bates <timothy.c.bates@gmail.com>"
  },
  {
    "package": "usaidplot",
    "on_cran": false,
    "archived_on": "2025-09-09 07:02:00",
    "url": "https://github.com/cranhaven/cranhaven.r-universe.dev",
    "branch": "package/usaidplot",
    "subdir": "usaidplot",
    "x_cran_comment_date": "2025-09-09",
    "x_cran_comment_event": "archived",
    "x_cran_comment_reason": "Requires archived package 'extrafont'",
    "package_url": "https://github.com/jacobpstein/usaid_plot",
    "package_bugreports": "https://github.com/jacobpstein/usaid_plot/issues",
    "maintainer": "Jacob Patterson-Stein <jacobpstein@gmail.com>"
  },
  {
    "package": "UtilityFrailtyPH12",
    "on_cran": false,
    "archived_on": "2025-09-17 08:02:00",
    "url": "https://github.com/cranhaven/cranhaven.r-universe.dev",
    "branch": "package/UtilityFrailtyPH12",
    "subdir": "UtilityFrailtyPH12",
    "x_cran_comment_date": "2025-09-17",
    "x_cran_comment_event": "archived",
    "x_cran_comment_reason": "Email to the maintainer is undeliverable",
    "maintainer": "Andrew G Chapple <achapp@lsuhsc.edu>"
  },
  {
    "package": "vanquish",
    "on_cran": false,
    "archived_on": "2025-09-17 09:02:00",
    "url": "https://github.com/cranhaven/cranhaven.r-universe.dev",
    "branch": "package/vanquish",
    "subdir": "vanquish",
    "x_cran_comment_date": "2025-09-17",
    "x_cran_comment_event": "archived",
    "x_cran_comment_reason": "Email to the maintainer is undeliverable",
    "maintainer": "Tao Jiang <tjiang8@ncsu.edu>"
  },
  {
    "package": "waffle",
    "on_cran": false,
    "archived_on": "2025-09-09 07:02:00",
    "url": "https://github.com/cranhaven/cranhaven.r-universe.dev",
    "branch": "package/waffle",
    "subdir": "waffle",
    "x_cran_comment_date": "2025-09-09",
    "x_cran_comment_event": "archived",
    "x_cran_comment_reason": "Requires archived package 'extrafont'",
    "maintainer": "Bob Rudis <bob@rud.is>"
  },
  {
    "package": "wkutils",
    "on_cran": false,
    "archived_on": "2025-09-10 00:02:00",
    "url": "https://github.com/cranhaven/cranhaven.r-universe.dev",
    "branch": "package/wkutils",
    "subdir": "wkutils",
    "x_cran_comment_date": "2025-09-10",
    "x_cran_comment_event": "archived",
    "x_cran_comment_reason": "The maintainer's request",
    "package_url": "https://paleolimbot.github.io/wkutils/,\nhttps://github.com/paleolimbot/wkutils",
    "package_bugreports": "https://github.com/paleolimbot/wkutils/issues",
    "maintainer": "Dewey Dunnington <dewey@fishandwhistle.net>"
  },
  {
    "package": "xkcd",
    "on_cran": false,
    "archived_on": "2025-09-09 07:02:00",
    "url": "https://github.com/cranhaven/cranhaven.r-universe.dev",
    "branch": "package/xkcd",
    "subdir": "xkcd",
    "x_cran_comment_date": "2025-09-09",
    "x_cran_comment_event": "archived",
    "x_cran_comment_reason": "Requires archived package 'extrafont'",
    "package_url": "",
    "maintainer": "Emilio Torres-Manzanera <torres@uniovi.es>"
  }
]
